yatrep/__init__.py
yatrep/cli.py
yatrep-0.0.2.dist-info/METADATA
yatrep-0.0.2.dist-info/WHEEL
yatrep-0.0.2.dist-info/top_level.txt
yatrep-0.0.2.dist-info/RECORD
