Metadata-Version: 2.1
Name: yatrep
Version: 0.0.2
Summary: Unity tests results xml parser tool
Home-page: UNKNOWN
License: UNKNOWN
Platform: UNKNOWN
Requires-Python: >=3.4
Provides-Extra: dev
Provides-Extra: test
